README.md
setup.cfg
setup.py
blobrl/__init__.py
blobrl/logger.py
blobrl/trainer.py
blobrl.egg-info/PKG-INFO
blobrl.egg-info/SOURCES.txt
blobrl.egg-info/dependency_links.txt
blobrl.egg-info/requires.txt
blobrl.egg-info/top_level.txt
blobrl/agents/__init__.py
blobrl/agents/agent_constant.py
blobrl/agents/agent_interface.py
blobrl/agents/agent_random.py
blobrl/agents/categorical_dqn.py
blobrl/agents/double_dqn.py
blobrl/agents/dqn.py
blobrl/environments/__init__.py
blobrl/explorations/__init__.py
blobrl/explorations/adaptative_epsilon_greedy.py
blobrl/explorations/epsilon_greedy.py
blobrl/explorations/greedy.py
blobrl/explorations/greedy_exploration_interface.py
blobrl/explorations/not_greedy.py
blobrl/memories/__init__.py
blobrl/memories/experience_replay.py
blobrl/memories/memory_interface.py
blobrl/networks/__init__.py
blobrl/networks/base_dueling_network.py
blobrl/networks/base_network.py
blobrl/networks/c51_network.py
blobrl/networks/simple_dueling_network.py
blobrl/networks/simple_network.py
blobrl/networks/utils.py
tests/__init__.py
tests/test_logger.py
tests/test_trainer.py
tests/train.py
tests/agents/__init__.py
tests/agents/test_agent_constant.py
tests/agents/test_agent_interface.py
tests/agents/test_agent_random.py
tests/agents/test_categorical_dqn.py
tests/agents/test_double_dqn.py
tests/agents/test_dqn.py
tests/environments/__init__.py
tests/explorations/__init__.py
tests/explorations/test_adaptative_epsilon_greedy.py
tests/explorations/test_epsilon_greedy.py
tests/explorations/test_greedy.py
tests/explorations/test_greedy_exploration_interface.py
tests/explorations/test_not_greedy.py
tests/memories/__init__.py
tests/memories/test_experience_replay.py
tests/memories/test_memory_interface.py
tests/networks/__init__.py
tests/networks/test_base_dueling_network.py
tests/networks/test_base_network.py
tests/networks/test_c51_network.py
tests/networks/test_simple_dueling_network.py
tests/networks/test_simple_network.py
tests/networks/test_utils.py