Metadata-Version: 2.1
Name: blobrl
Version: 0.1.3
Summary: Reinforcement learning with pytorch 
Home-page: https://github.com/french-ai/reinforcement
Author: french ai team
License: Apache-2.0
Download-URL: https://github.com/french-ai/reinforcement/archive/V0.1.3.tar.gz
Platform: UNKNOWN
Classifier: Development Status :: 3 - Alpha
Classifier: License :: OSI Approved :: Apache Software License
Classifier: Programming Language :: Python
Classifier: Programming Language :: Python :: 3.6
Classifier: Programming Language :: Python :: 3.7
Classifier: Programming Language :: Python :: 3.8
Classifier: Topic :: Software Development :: Libraries
Classifier: Topic :: Software Development :: Libraries :: Python Modules
Classifier: Intended Audience :: Developers
Requires-Python: >=3.6.1
Provides-Extra: dev
Provides-Extra: notebook
